bimbmaan/__init__.py
bimbmaan/__metadata__.py
bimbmaan/manager.py
bimbmaan-0.2.dist-info/LICENSE
bimbmaan-0.2.dist-info/METADATA
bimbmaan-0.2.dist-info/WHEEL
bimbmaan-0.2.dist-info/entry_points.txt
bimbmaan-0.2.dist-info/top_level.txt
bimbmaan-0.2.dist-info/RECORD
