Metadata-Version: 2.1
Name: bimbmaan
Version: 0.2
Summary: bimbmaan: A Shaktiman to process high quality images for research publication
Author-email: Vishal Kumar Sahu <mail@vishalkumarsahu.in>
Project-URL: Homepage, https://github.com/TheBiomics/bimbmaan
Project-URL: Issues, https://github.com/TheBiomics/bimbmaan/issues
Classifier: Operating System :: OS Independent
Classifier: Intended Audience :: Science/Research
Classifier: Programming Language :: Python :: 3.8
Classifier: Programming Language :: Python :: 3.9
Classifier: Programming Language :: Python :: 3.10
Requires-Python: >=3.8
License-File: LICENSE
Requires-Dist: UtilityLib
Requires-Dist: imageio
Requires-Dist: fitz
Requires-Dist: PyMuPDF
